[
	{
		"formfactor":"phone",
		"type":"iPhone",
		"model": "7S",
		"network":[0,1,4],
		"size":["32GB","128GB","256GB"],
		"value":{
			"working":123.12,
			"broken":100.12
		}
	},
	{
		"formfactor":"phone",
		"type":"iPhone",
		"model": "7",
		"network":[0,1,4],
		"size":["32GB","128GB","256GB"],
		"value":{
			"working":123.12,
			"broken":100.12
		}
	},
	{
		"formfactor":"phone",
		"type":"smartphone",
		"network":[0,1,4],
		"size":["32GB","128GB","256GB"],
		"value":{
			"working":123.12,
			"broken":100.12
		}
	},
	{
		"formfactor":"phone",
		"type":"smartphone",
		"network":[0,1,4],
		"size":["32GB","128GB","256GB"],
		"value":{
			"working":123.12,
			"broken":100.12
		}
	},
	{
		"formfactor":"phone",
		"type":"smartphone",
		"network":[0,1,4],
		"size":["32GB","128GB","256GB"],
		"value":{
			"working":123.12,
			"broken":100.12
		}
	},
	{
		"formfactor":"phone",
		"type":"smartphone",
		"network":[0,1,4],
		"size":["32GB","128GB","256GB"],
		"value":{
			"working":123.12,
			"broken":100.12
		}
	},
	{
		"formfactor":"phone",
		"type":"smartphone",
		"network":[0,1,4],
		"size":["32GB","128GB","256GB"],
		"value":{
			"working":123.12,
			"broken":100.12
		}
	},
	{
		"formfactor":"phone",
		"type":"smartphone",
		"network":[0,1,4],
		"size":["32GB","128GB","256GB"],
		"value":{
			"working":123.12,
			"broken":100.12
		}
	},
	{
		"formfactor":"phone",
		"type":"smartphone",
		"network":[0,1,4],
		"size":["32GB","128GB","256GB"],
		"value":{
			"working":123.12,
			"broken":100.12
		}
	}
]